AICS/experiments/实验答案/chap6&7/lab6_code/src/serial_pe/serial_pe.v
module serial_pe(
  input                clk,
  input                rst_n,
  input  signed [15:0] neuron,
  input  signed [15:0] weight,
  input         [ 1:0] ctl,
  input                vld_i,
  output        [31:0] result,
  output reg           vld_o
);

/*乘法器*/  /*TODO*/
wire signed [31:0] mult_res = neuron * weight;
//________________________________________;
reg [31:0] psum_r;

/*加法器*/  /*TODO*/
wire [31:0] psum_d = ctl[0] ? mult_res : psum_r + mult_res;
//_________________________________________________;

/*部分和寄存器*/
always@(posedge clk or negedge rst_n)
if(!rst_n) begin
  psum_r <= 32'h0;
end else if(vld_i) begin
  psum_r <= psum_d;
end

always@(posedge clk or negedge rst_n)
if(!rst_n) begin
  vld_o <= 1'b0;
  //____________________________________________________
end else if(ctl[1] && vld_i) begin
  vld_o <= 1'b1;
end else begin
  vld_o <= 1'b0;
end

assign result = psum_r;

endmodule

AICS/experiments/实验答案/chap6&7/lab6_code/sim_iverilog/tb_top_0.v
`timescale 1ns/1ps

module tb_top_0;
localparam WIDTH = 32;

reg        clk; // clk
reg        rst_n; // reset

initial begin
    clk = 1'b0;
    forever #0.5 clk = ~clk;
end
initial begin
    rst_n = 1'b0;
    #10 rst_n = 1'b1;
end
initial begin
    // 创建serial_sim目录并dump波形文件
    $dumpfile("serial_sim/serial_pe.vcd");
    $dumpvars(0, tb_top_0);
end
initial begin
    #10000;
    $finish;
end

reg [7  :0] inst[3:0];
reg [511:0] neuron[139:0];
reg [511:0] weight[139:0];
reg [ 44:0] result[3:0];  // 修改位宽以匹配数据生成脚本

initial
begin
  $readmemh("../data/inst", inst);
  $readmemh("../data/neuron", neuron);
  $readmemh("../data/weight", weight);
  $readmemb("../data/result", result);
end

reg [ 1:0]   inst_addr;
reg [12:0]   iter;
reg [15:0]   neuron_addr;
reg [15:0]   weight_addr;

wire [  7:0] pe_inst        = inst[inst_addr];
wire [511:0] pe_weight_line = weight[weight_addr[15:5]];
wire [511:0] pe_neuron_line = neuron[neuron_addr[15:5]];
wire [ 15:0] pe_weight      = pe_weight_line[(16*(31-weight_addr[4:0]))+:16];
wire [ 15:0] pe_neuron      = pe_neuron_line[(16*(31-neuron_addr[4:0]))+:16];
wire [1:0] pe_ctl;
assign pe_ctl[0] = (iter[12:0] == 13'h0);
assign pe_ctl[1] = (iter[12:5] == (pe_inst[7:0] - 1'b1)) && (iter[4:0] == 5'h1f);

reg pe_vld_i;
always@(posedge clk or negedge rst_n) begin
  if(!rst_n) begin
    pe_vld_i <= 1'b0;
  end else if((inst_addr == 2'h0) && (neuron_addr == 16'h0) && (weight_addr == 16'h0)) begin
    pe_vld_i <= 1'b1;
  end else if(pe_ctl[1] && pe_vld_i && (inst_addr == 2'h3)) begin
    pe_vld_i <= 1'b0;
  end
end

//always@(posedge clk or negedge rst_n) begin
//  if(!rst_n) begin
//    iter <= 13'b0;
//  end else if(pe_ctl[1] && pe_vld_i && (inst_addr == 2'h3)) begin
//    iter <= 13'b0;
//  end else if(pe_vld_i) begin
//    iter <= iter + 1'b1;
//  end
//end
always@(posedge clk or negedge rst_n) begin
  if(!rst_n) begin
    iter <= 13'b0;
  end else if(pe_ctl[1] && pe_vld_i) begin  // 每个指令完成后都重置iter
    iter <= 13'b0;
  end else if(pe_vld_i) begin
    iter <= iter + 1'b1;
  end
end


always@(posedge clk or negedge rst_n) begin
  if(!rst_n) begin
    inst_addr <= 2'b0;
  end else if(pe_ctl[1] && pe_vld_i && (inst_addr != 2'h3)) begin
    inst_addr <= inst_addr + 1'b1;
  end
end

always@(posedge clk or negedge rst_n) begin
  if(!rst_n) begin
    weight_addr <= 16'h0;
  end else if(pe_vld_i) begin
    weight_addr <= weight_addr + 1'b1;
  end
end

always@(posedge clk or negedge rst_n) begin
  if(!rst_n) begin
    neuron_addr <= 16'h0;
  end else if(pe_vld_i) begin
    neuron_addr <= neuron_addr + 1'b1;
  end
end

wire [31:0] pe_result;
wire pe_vld_o;
serial_pe u_serial_pe (
  .clk                  (clk      ),
  .rst_n                (rst_n    ),
  .neuron               (pe_neuron),
  .weight               (pe_weight),
  .ctl                  (pe_ctl   ),
  .vld_i                (pe_vld_i ),
  .result               (pe_result),
  .vld_o                (pe_vld_o )
);

reg [1:0] result_addr;
reg compare_pass;
always@(posedge clk or negedge rst_n) begin
  if(!rst_n) begin
    result_addr <= 2'h0;
  end else if(pe_vld_o) begin
    result_addr <= result_addr + 1'b1;
  end
end

always@(posedge clk or negedge rst_n) begin
  if(!rst_n) begin
    compare_pass <= 1'b1;
  end else if(pe_vld_o && (pe_result != result[result_addr][31:0])) begin  // 只比较低32位
    $display("FAIL: num.%d result not correct!!! Expected: %h, Got: %h", result_addr, result[result_addr][31:0], pe_result);
    compare_pass <= 1'b0;
  end else if(pe_vld_o && (pe_result == result[result_addr][31:0])) begin
    $display("INFO: num.%d result is correct.", result_addr);
  end
end

endmodule

AICS/experiments/实验答案/chap6&7/lab6_code/sim_iverilog/serial_sim/serial_pe.vcd
$date
	Wed Jun  4 00:50:34 2025
$end
$version
	Icarus Verilog
$end
$timescale
	1ps
$end
$scope module tb_top_0 $end
$var wire 8 ! pe_inst [7:0] $end
$var wire 512 " pe_neuron_line [511:0] $end
$var wire 512 # pe_weight_line [511:0] $end
$var wire 16 $ pe_weight [15:0] $end
$var wire 1 % pe_vld_o $end
$var wire 32 & pe_result [31:0] $end
$var wire 16 ' pe_neuron [15:0] $end
$var wire 2 ( pe_ctl [1:0] $end
$var reg 1 ) clk $end
$var reg 1 * compare_pass $end
$var reg 2 + inst_addr [1:0] $end
$var reg 13 , iter [12:0] $end
$var reg 16 - neuron_addr [15:0] $end
$var reg 1 . pe_vld_i $end
$var reg 2 / result_addr [1:0] $end
$var reg 1 0 rst_n $end
$var reg 16 1 weight_addr [15:0] $end
$scope module u_serial_pe $end
$var wire 1 ) clk $end
$var wire 2 2 ctl [1:0] $end
$var wire 16 3 neuron [15:0] $end
$var wire 32 4 result [31:0] $end
$var wire 1 0 rst_n $end
$var wire 1 . vld_i $end
$var wire 16 5 weight [15:0] $end
$var wire 32 6 psum_d [31:0] $end
$var wire 32 7 mult_res [31:0] $end
$var reg 32 8 psum_r [31:0] $end
$var reg 1 % vld_o $end
$upscope $end
$upscope $end
$enddefinitions $end
#0
$dumpvars
b0 8
bx 7
bx 6
bx 5
b0 4
bx 3
bx 2
bx 1
00
bx /
x.
bx -
bx ,
bx +
x*
0)
bx (
bx '
b0 &
0%
bx $
bx #
bx "
bx !
$end
#500
b11101111000101011101101001100010 6
b11101111000101011101101001100010 7
b1001010101000010 $
b1001010101000010 5
b10010101010000101010011011110101110010111001010001101000010101111111001101101101101010000110000010110111011001100011001010011110111101000101011110101111011000111000101000101001101101000001010000110110111100011000010101111111011111011001111010001111101110001000010111001101101000100010101110100110110111000100010000110001111001001001110000000011010000100110011011010110111111011101110010000001101111000101000100001010101001111110110010111010011111111100111011100000000011111111101010001110001111011100011100100110 #
b10100010010001 '
b10100010010001 3
b101000100100010111100011110001011001010110000001000011000010100111000101101101000000100000010111011101111111001100001000110101011000011010010111010000000111111011010010000011100111000000011111010100011011010101110100010100110111001110000101100011011011110000101101001001011011100111010001001110101111100110111011111111011100100100110100010111010110010111001001101010100010100011111111101010011110100100101000111010111110100101100110110001111101001011011101000000111000001101111001011010010011100011101110110110 "
0.
b1 (
b1 2
b0 ,
b10100 !
b0 +
b0 1
b0 -
b0 /
1*
1)
#1000
0)
#1500
1)
#2000
0)
#2500
1)
#3000
0)
#3500
1)
#4000
0)
#4500
1)
#5000
0)
#5500
1)
#6000
0)
#6500
1)
#7000
0)
#7500
1)
#8000
0)
#8500
1)
#9000
0)
#9500
1)
#10000
0)
10
#10500
1.
1)
#11000
0)
#11500
b11000101000001001101111100000111 6
b111100011110001 '
b111100011110001 3
b11010101111011110000010010100101 7
b1010011011110101 $
b1010011011110101 5
b11101111000101011101101001100010 &
b11101111000101011101101001100010 4
b11101111000101011101101001100010 8
b1 -
b1 1
b0 (
b0 2
b1 ,
1)
#12000
0)
#12500
b1100101110010100 $
b1100101110010100 5
b11101011001111011011101110000000 7
b110010101100000 '
b110010101100000 3
b10110000010000101001101010000111 6
b10 ,
b10 1
b10 -
b11000101000001001101111100000111 &
b11000101000001001101111100000111 4
b11000101000001001101111100000111 8
1)
#13000
0)
#13500
b11001011100101010111001011101101 6
b100001100001010 '
b100001100001010 3
b11011010100101101100001100110 7
b110100001010111 $
b110100001010111 5
b10110000010000101001101010000111 &
b10110000010000101001101010000111 4
b10110000010000101001101010000111 8
b11 -
b11 1
b11 ,
1)
#14000
0)
#14500
b1111001101101101 $
b1111001101101101 5
b11111010011011011100001001101001 7
b111000101101101 '
b111000101101101 3
b11000110000000110011010101010110 6
b100 ,
b100 1
b100 -
b11001011100101010111001011101101 &
b11001011100101010111001011101101 4
b11001011100101010111001011101101 8
1)
#15000
0)
#15500
b11000101010100100011111100110110 6
b1000000101 '
b1000000101 3
b11111111010011110000100111100000 7
b1010100001100000 $
b1010100001100000 5
b11000110000000110011010101010110 &
b11000110000000110011010101010110 4
b11000110000000110011010101010110 8
b101 -
b101 1
b101 ,
1)
#16000
0)
#16500
b1011011101100110 $
b1011011101100110 5
b1001101001011001011001101000 7
b1101110111111100 '
b1101110111111100 3
b11001110111101111101010110011110 6
b110 ,
b110 1
b110 -
b11000101010100100011111100110110 &
b11000101010100100011111100110110 4
b11000101010100100011111100110110 8
1)
#17000
0)
#17500
b11000010110000000000110001010100 6
b1100001000110101 '
b1100001000110101 3
b11110011110010000011011010110110 7
b11001010011110 $
b11001010011110 5
b11001110111101111101010110011110 &
b11001110111101111101010110011110 4
b11001110111101111101010110011110 8
b111 -
b111 1
b111 ,
1)
#18000
0)
#18500
b1111010001010111 $
b1111010001010111 5
b11111011100011010111001100010011 7
b110000110100101 '
b110000110100101 3
b10111110010011010111111101100111 6
b1000 ,
b1000 1
b1000 -
b11000010110000000000110001010100 &
b11000010110000000000110001010100 4
b11000010110000000000110001010100 8
1)
#19000
0)
#19500
b11001101011000010010110001100100 6
b1101000000011111 '
b1101000000011111 3
b1111000100111010110011111101 7
b1010111101100011 $
b1010111101100011 5
b10111110010011010111111101100111 &
b10111110010011010111111101100111 4
b10111110010011010111111101100111 8
b1001 -
b1001 1
b1001 ,
1)
#20000
0)
#20500
b1000101000101001 $
b1000101000101001 5
b100010101111111000011011111011 7
b1011010010000011 '
b1011010010000011 3
b11110000001000001011001101011111 6
b1010 ,
b1010 1
b1010 -
b11001101011000010010110001100100 &
b11001101011000010010110001100100 4
b11001101011000010010110001100100 8
1)
#21000
0)
#21500
b1101110001101100111111101011 6
b1001110000000111 '
b1001110000000111 3
b11101101001100001110010001100 7
b1011010000010100 $
b1011010000010100 5
b11110000001000001011001101011111 &
b11110000001000001011001101011111 4
b11110000001000001011001101011111 8
b1011 -
b1011 1
b1011 ,
1)
#22000
0)
#22500
b11011011110001 $
b11011011110001 5
b11110110101001011111100010011101 7
b1101010001101101 '
b1101010001101101 3
b100011011001100100010001000 6
b1100 ,
b1100 1
b1100 -
b1101110001101100111111101011 &
b1101110001101100111111101011 4
b1101110001101100111111101011 8
1)
#23000
0)
#23500
b11010111111000100101100101110100 6
b101110100010100 '
b101110100010100 3
b11010011011101011001000011101100 7
b1000010101111111 $
b1000010101111111 5
b100011011001100100010001000 &
b100011011001100100010001000 4
b100011011001100100010001000 8
b1101 -
b1101 1
b1101 ,
1)
#24000
0)
#24500
b111110110011110 $
b111110110011110 5
b11101110110001000010111111011110 7
b1101110011100001 '
b1101110011100001 3
b11000110101001101000100101010010 6
b1110 ,
b1110 1
b1110 -
b11010111111000100101100101110100 &
b11010111111000100101100101110100 4
b11010111111000100101100101110100 8
1)
#25000
0)
#25500
b10011011000010100000001000011010 6
b110001101101111 '
b110001101101111 3
b11010100011000110111100011001000 7
b1000111110111000 $
b1000111110111000 5
b11000110101001101000100101010010 &
b11000110101001101000100101010010 4
b11000110101001101000100101010010 8
b1111 -
b1111 1
b1111 ,
1)
#26000
0)
#26500
b1000010111001101 $
b1000010111001101 5
b11111010100111001111011001110101 7
b101101001001 '
b101101001001 3
b10010101101001101111100010001111 6
b10000 ,
b10000 1
b10000 -
b10011011000010100000001000011010 &
b10011011000010100000001000011010 4
b10011011000010100000001000011010 8
1)
#27000
0)
#27500
b1101101001010101110111000001011 6
b110111001110100 '
b110111001110100 3
b11010111100000111111010101111100 7
b1010001000101011 $
b1010001000101011 5
b10010101101001101111100010001111 &
b10010101101001101111100010001111 4
b10010101101001101111100010001111 8
b10001 -
b10001 1
b10001 ,
1)
#28000
0)
#28500
b1010011011011100 $
b1010011011011100 5
b11100100100101001101111101001000 7
b100111010111110 '
b100111010111110 3
b1010001101111111100110101010011 6
b10010 ,
b10010 1
b10010 -
b1101101001010101110111000001011 &
b1101101001010101110111000001011 4
b1101101001010101110111000001011 8
1)
#29000
0)
#29500
b1101111010100001100100000100010 6
b110111011111111 '
b110111011111111 3
b11101100100001111101011001111 7
b100010000110001 $
b100010000110001 5
b1010001101111111100110101010011 &
b1010001101111111100110101010011 4
b1010001101111111100110101010011 8
b10011 -
b10011 1
b10011 ,
1)
#30000
0)
#30500
b1110010010011100 $
b1110010010011100 5
b11110011110001010011101011101100 7
b111001001001101 '
b111001001001101 3
b1100011000101100000001100001110 6
b10100 ,
b10100 1
b10100 -
b1101111010100001100100000100010 &
b1101111010100001100100000100010 4
b1101111010100001100100000100010 8
1)
#31000
0)
#31500
b1100011011000100001001100000000 6
b1011101011001 '
b1011101011001 3
b10011000000111111110010 7
b1101000010 $
b1101000010 5
b1100011000101100000001100001110 &
b1100011000101100000001100001110 4
b1100011000101100000001100001110 8
b10101 -
b10101 1
b10101 ,
1)
#32000
0)
#32500
b110011011010110 $
b110011011010110 5
b101101111101011110000010011100 7
b111001001101010 '
b111001001101010 3
b10010001010101111111001110011100 6
b10110 ,
b10110 1
b10110 -
b1100011011000100001001100000000 &
b1100011011000100001001100000000 4
b1100011011000100001001100000000 8
1)
#33000
0)
#33500
b10010010010101000000010011000000 6
b1000101000111111 '
b1000101000111111 3
b111111000001000100100100 7
b1111110111011100 $
b1111110111011100 5
b10010001010101111111001110011100 &
b10010001010101111111001110011100 4
b10010001010101111111001110011100 8
b10111 -
b10111 1
b10111 ,
1)
#34000
0)
#34500
b1000000110111100 $
b1000000110111100 5
b1010100111011010101110011000 7
b1110101001111010 '
b1110101001111010 3
b10011100111100011011000001011000 6
b11000 ,
b11000 1
b11000 -
b10010010010101000000010011000000 &
b10010010010101000000010011000000 4
b10010010010101000000010011000000 8
1)
#35000
0)
#35500
b10110100011100001111000010011100 6
b100101000111010 '
b100101000111010 3
b10111011111110100000001000100 7
b101000100001010 $
b101000100001010 5
b10011100111100011011000001011000 &
b10011100111100011011000001011000 4
b10011100111100011011000001011000 8
b11001 -
b11001 1
b11001 ,
1)
#36000
0)
#36500
b1010011111101100 $
b1010011111101100 5
b1111100011101100100001100 7
b1111101001011001 '
b1111101001011001 3
b10110110011000101100100110101000 6
b11010 ,
b11010 1
b11010 -
b10110100011100001111000010011100 &
b10110100011100001111000010011100 4
b10110100011100001111000010011100 8
1)
#37000
0)
#37500
b11001011100100110101100110110100 6
b1011000111110100 '
b1011000111110100 3
b10101001100001001000000001100 7
b1011101001111111 $
b1011101001111111 5
b10110110011000101100100110101000 &
b10110110011000101100100110101000 4
b10110110011000101100100110101000 8
b11011 -
b11011 1
b11011 ,
1)
#38000
0)
#38500
b1100111011100000 $
b1100111011100000 5
b1101111101011101100000000000 7
b1011011101000000 '
b1011011101000000 3
b11011001100010010011000110110100 6
b11100 ,
b11100 1
b11100 -
b11001011100100110101100110110100 &
b11001011100100110101100110110100 4
b11001011100100110101100110110100 8
1)
#39000
0)
#39500
b11010111100101111100110010000000 6
b1110000011011110 '
b1110000011011110 3
b11111110000011101001101011001100 7
b111111111010 $
b111111111010 5
b11011001100010010011000110110100 &
b11011001100010010011000110110100 4
b11011001100010010011000110110100 8
b11101 -
b11101 1
b11101 ,
1)
#40000
0)
#40500
b1000111000111101 $
b1000111000111101 5
b11010111110111101100100010010110 7
b101101001001110 '
b101101001001110 3
b10101111011101101001010100010110 6
b11110 ,
b11110 1
b11110 -
b11010111100101111100110010000000 &
b11010111100101111100110010000000 4
b11010111100101111100110010000000 8
1)
#41000
0)
#41500
b10100010001100111110110000011010 6
b11101110110110 '
b11101110110110 3
b11110010101111010101011100000100 7
b1100011100100110 $
b1100011100100110 5
b10101111011101101001010100010110 &
b10101111011101101001010100010110 4
b10101111011101101001010100010110 8
b11111 -
b11111 1
b11111 ,
1)
#42000
0)
#42500
b10000111000000110110011100010100100101011111111110100110001011101110000010010000100001111110110100000110101111101001000111111011101101111110000110111101100101001010110011100010010101101000001010100001011110110001111000010110111010001011110111001101001010010011010111010101110000000011110100001000110001111100001010001010010010111100111000101101100100101111011001101101110011011001011110010000001011010111100101011001110101100110111101101000010010010110001011111001001100011011010111101110001100100101111010010111 #
b1000011100000011 $
b1000011100000011 5
b11111011101110000001101001101011100101011001101010000011001100000111000011110101100011111011000101100001110111000101110011011100000111101100001100100001111010111101101111111111000110110110000110100111000100010100010101110000101101001111010000001000011111110110010100010010011111001110001010111100001010010011011010111100110100010011101100100100010011010110110101001110110011101101100110001100100100100101100101010011100101111011101110111001100001001010100011001110001001000000001000000111010011000101000010000100 "
b10000001011111101100101000 7
b1111101110111000 '
b1111101110111000 3
b10100100001110011110011101000010 6
b100000 ,
b100000 1
b100000 -
b10100010001100111110110000011010 &
b10100010001100111110110000011010 4
b10100010001100111110110000011010 8
1)
#43000
0)
#43500
b10101110110111010000010010011110 6
b1101001101011 '
b1101001101011 3
b1010101000110001110101011100 7
b110011100010100 $
b110011100010100 5
b10100100001110011110011101000010 &
b10100100001110011110011101000010 4
b10100100001110011110011101000010 8
b100001 -
b100001 1
b100001 ,
1)
#44000
0)
#44500
b1001010111111111 $
b1001010111111111 5
b101100000011101010011001100110 7
b1001010110011010 '
b1001010110011010 3
b11011010111010111010101100000100 6
b100010 ,
b100010 1
b100010 -
b10101110110111010000010010011110 &
b10101110110111010000010010011110 4
b10101110110111010000010010011110 8
1)
#45000
0)
#45500
b110101101100101110110100100 6
b1000001100110000 '
b1000001100110000 3
b101011110010101011001010100000 7
b1010011000101110 $
b1010011000101110 5
b11011010111010111010101100000100 &
b11011010111010111010101100000100 4
b11011010111010111010101100000100 8
b100011 -
b100011 1
b100011 ,
1)
#46000
0)
#46500
b1110000010010000 $
b1110000010010000 5
b11110010001000001110100111010000 7
b111000011110101 '
b111000011110101 3
b11111000110101110100011101110100 6
b100100 ,
b100100 1
b100100 -
b110101101100101110110100100 &
b110101101100101110110100100 4
b110101101100101110110100100 8
1)
#47000
0)
#47500
b101101100001001010010101010001 6
b1000111110110001 '
b1000111110110001 3
b110100101011010101110111011101 7
b1000011111101101 $
b1000011111101101 5
b11111000110101110100011101110100 &
b11111000110101110100011101110100 4
b11111000110101110100011101110100 8
b100101 -
b100101 1
b100101 ,
1)
#48000
0)
#48500
b11010111110 $
b11010111110 5
b10100100111100100101001000 7
b110000111011100 '
b110000111011100 3
b110000000110000110111010011001 6
b100110 ,
b100110 1
b100110 -
b101101100001001010010101010001 &
b101101100001001010010101010001 4
b101101100001001010010101010001 8
1)
#49000
0)
#49500
b1000001100000001011001001101 6
b101110011011100 '
b101110011011100 3
b11011000000101111010011110110100 7
b1001000111111011 $
b1001000111111011 5
b110000000110000110111010011001 &
b110000000110000110111010011001 4
b110000000110000110111010011001 8
b100111 -
b100111 1
b100111 ,
1)
#50000
0)
#50500
b1011011111100001 $
b1011011111100001 5
b11110111010101010110111001100011 7
b1111011000011 '
b1111011000011 3
b11111111100001011000010010110000 6
b101000 ,
b101000 1
b101000 -
b1000001100000001011001001101 &
b1000001100000001011001001101 4
b1000001100000001011001001101 8
1)
#51000
0)
#51500
b11110110101110001001111110001100 6
b10000111101011 '
b10000111101011 3
b11110111001100110001101011011100 7
b1011110110010100 $
b1011110110010100 5
b11111111100001011000010010110000 &
b11111111100001011000010010110000 4
b11111111100001011000010010110000 8
b101001 -
b101001 1
b101001 ,
1)
#52000
0)
#52500
b1010110011100010 $
b1010110011100010 5
b1011101100001000101100011110 7
b1101101111111111 '
b1101101111111111 3
b10011010010010101010101010 6
b101010 ,
b101010 1
b101010 -
b11110110101110001001111110001100 &
b11110110101110001001111110001100 4
b11110110101110001001111110001100 8
1)
#53000
0)
#53500
b1011101010011010011111101100 6
b1101101100001 '
b1101101100001 3
b1001010000000111110101000010 7
b101011010000010 $
b101011010000010 5
b10011010010010101010101010 &
b10011010010010101010101010 4
b10011010010010101010101010 8
b101011 -
b101011 1
b101011 ,
1)
#54000
0)
#54500
b1010000101111011 $
b1010000101111011 5
b100000110101011111011000101011 7
b1010011100010001 '
b1010011100010001 3
b101100011111111001111000010111 6
b101100 ,
b101100 1
b101100 -
b1011101010011010011111101100 &
b1011101010011010011111101100 4
b1011101010011010011111101100 8
1)
#55000
0)
#55500
b110100101010001011010110110111 6
b100010101110000 '
b100010101110000 3
b1000001010010001011110100000 7
b1111000010110 $
b1111000010110 5
b101100011111111001111000010111 &
b101100011111111001111000010111 4
b101100011111111001111000010111 8
b101101 -
b101101 1
b101101 ,
1)
#56000
0)
#56500
b1110100010111101 $
b1110100010111101 5
b110110100011011100000100100 7
b1011010011110100 '
b1011010011110100 3
b111011011110100110110111011011 6
b101110 ,
b101110 1
b101110 -
b110100101010001011010110110111 &
b110100101010001011010110110111 4
b110100101010001011010110110111 8
1)
#57000
0)
#57500
b111001110010100111110100110010 6
b100001111111 '
b100001111111 3
b11111110010100000000111101010111 7
b1100110100101001 $
b1100110100101001 5
b111011011110100110110111011011 &
b111011011110100110110111011011 4
b111011011110100110110111011011 8
b101111 -
b101111 1
b101111 ,
1)
#58000
0)
#58500
b11010111010101 $
b11010111010101 5
b10101010000001101000111111010 7
b110010100010010 '
b110010100010010 3
b1001111000010110100111100101100 6
b110000 ,
b110000 1
b110000 -
b111001110010100111110100110010 &
b111001110010100111110100110010 4
b111001110010100111110100110010 8
1)
#59000
0)
#59500
b101111111100001001000100000110 6
b111110011100010 '
b111110011100010 3
b11100000111001010100000111011010 7
b1100000000111101 $
b1100000000111101 5
b1001111000010110100111100101100 &
b1001111000010110100111100101100 4
b1001111000010110100111100101100 8
b110001 -
b110001 1
b110001 ,
1)
#60000
0)
#60500
b100011000111 $
b100011000111 5
b11111101101011001000101111011111 7
b1011110000101001 '
b1011110000101001 3
b101101100111010001110011100101 6
b110010 ,
b110010 1
b110010 -
b101111111100001001000100000110 &
b101111111100001001000100000110 4
b101111111100001001000100000110 8
1)
#61000
0)
#61500
b100000011110010001011000111101 6
b11011010111100 '
b11011010111100 3
b11110010110110111111100101011000 7
b1100001010001010 $
b1100001010001010 5
b101101100111010001110011100101 &
b101101100111010001110011100101 4
b101101100111010001110011100101 8
b110011 -
b110011 1
b110011 ,
1)
#62000
0)
#62500
b100101111001110 $
b100101111001110 5
b11110010001001101010011001111010 7
b1101000100111011 '
b1101000100111011 3
b10010100111111011110010110111 6
b110100 ,
b110100 1
b110100 -
b100000011110010001011000111101 &
b100000011110010001011000111101 4
b100000011110010001011000111101 8
1)
#63000
0)
#63500
b11001000101011111100110100001 6
b10010001001101 '
b10010001001101 3
b110011101100011110011101010 7
b10110110010010 $
b10110110010010 5
b10010100111111011110010110111 &
b10010100111111011110010110111 4
b10010100111111011110010110111 8
b110101 -
b110101 1
b110101 ,
1)
#64000
0)
#64500
b1111011001101101 $
b1111011001101101 5
b11111011111010010111111000110110 7
b110110101001110 '
b110110101001110 3
b10100111111110111011111010111 6
b110110 ,
b110110 1
b110110 -
b11001000101011111100110100001 &
b11001000101011111100110100001 4
b11001000101011111100110100001 8
1)
#65000
0)
#65500
b11110101011010011111011010110 6
b1100111011011001 '
b1100111011011001 3
b1001101011011100011011111111 7
b1100110110010111 $
b1100110110010111 5
b10100111111110111011111010111 &
b10100111111110111011111010111 4
b10100111111110111011111010111 8
b110111 -
b110111 1
b110111 ,
1)
#66000
0)
#66500
b1001000000101101 $
b1001000000101101 5
b110010011010111101010110101010 7
b1000110010010010 '
b1000110010010010 3
b1010001000110010001010010000000 6
b111000 ,
b111000 1
b111000 -
b11110101011010011111011010110 &
b11110101011010011111011010110 4
b11110101011010011111011010110 8
1)
#67000
0)
#67500
b1111011011100000101110101011011 6
b101100101010011 '
b101100101010011 3
b101010010101110100100011011011 7
b111100101011001 $
b111100101011001 5
b1010001000110010001010010000000 &
b1010001000110010001010010000000 4
b1010001000110010001010010000000 8
b111001 -
b111001 1
b111001 ,
1)
#68000
0)
#68500
b1101011001101111 $
b1101011001101111 5
b10000111011100001110000010101 7
b1001011110111011 '
b1001011110111011 3
b10001100010111100111100101110000 6
b111010 ,
b111010 1
b111010 -
b1111011011100000101110101011011 &
b1111011011100000101110101011011 4
b1111011011100000101110101011011 8
1)
#69000
0)
#69500
b1101111101010000000000000010100 6
b1011100110000100 '
b1011100110000100 3
b11100011010010011000011010100100 7
b110100001001001 $
b110100001001001 5
b10001100010111100111100101110000 &
b10001100010111100111100101110000 4
b10001100010111100111100101110000 8
b111011 -
b111011 1
b111011 ,
1)
#70000
0)
#70500
b110001011111001 $
b110001011111001 5
b11011110010010100000110001011110 7
b1010100011001110 '
b1010100011001110 3
b1001101111100100000110001110010 6
b111100 ,
b111100 1
b111100 -
b1101111101010000000000000010100 &
b1101111101010000000000000010100 4
b1101111101010000000000000010100 8
1)
#71000
0)
#71500
b1010100111011111110001111011100 6
b10010000000010 '
b10010000000010 3
b110111111011101011101101010 7
b11000110110101 $
b11000110110101 5
b1001101111100100000110001110010 &
b1001101111100100000110001110010 4
b1001101111100100000110001110010 8
b111101 -
b111101 1
b111101 ,
1)
#72000
0)
#72500
b1110111000110010 $
b1110111000110010 5
b11111111011111100001010011011000 7
b11101001100 '
b11101001100 3
b1010100011011011111100010110100 6
b111110 ,
b111110 1
b111110 -
b1010100111011111110001111011100 &
b1010100111011111110001111011100 4
b1010100111011111110001111011100 8
1)
#73000
0)
#73500
b1110010001011011110111010010000 6
b101000010000100 '
b101000010000100 3
b11101101111111111010111011100 7
b101111010010111 $
b101111010010111 5
b1010100011011011111100010110100 &
b1010100011011011111100010110100 4
b1010100011011011111100010110100 8
b111111 -
b111111 1
b111111 ,
1)
#74000
0)
#74500
b10111011010111000000011011110010011001000010011111000111101010111101101010010000010000011010011110001001111111100000000101000111010111111100110000101011100101000001101001011111000100010001010110110011010000011011111010100011010110000001001101100011100101110100110000101100101001001001000111001110011001110010001011111001001100111000010010010011011010010111100001010110110000101000011101110011101110011011000101111110000001110001010001100011010110101000111001010000000110101000100010000100110011100111010010010101 #
b1011101101011100 $
b1011101101011100 5
b10111000111011101100111000001111111101111111111010110010100101010100000101011010011010000000110111100000011101010110100010101100101010010010100111110100101100011001100011111110011110010100000101011000101011110011001001011010001110100000110100010001011111011101101100111100100010011001110001101111110101100101010101001000100010100010010001010011010100101111110011111111100100001100001110001100000100100101110110000010101111100111111000001000110110110011001001111010101000011011101000010011010101100111010101010010 "
b10011000011100100111110001000 7
b1011100011101110 '
b1011100011101110 3
b10000101001111000011111000011000 6
b1000000 ,
b1000000 1
b1000000 -
b1110010001011011110111010010000 &
b1110010001011011110111010010000 4
b1110010001011011110111010010000 8
1)
#75000
0)
#75500
b10000011111000010110001001000110 6
b1100111000001111 '
b1100111000001111 3
b11111110101001010010010000101110 7
b11011110010 $
b11011110010 5
b10000101001111000011111000011000 &
b10000101001111000011111000011000 4
b10000101001111000011111000011000 8
b1000001 -
b1000001 1
b1000001 ,
1)
#76000
0)
#76500
b110010000100111 $
b110010000100111 5
b11111100110111011111111110110010 7
b1111011111111110 '
b1111011111111110 3
b10000000101111110110000111111000 6
b1000010 ,
b1000010 1
b1000010 -
b10000011111000010110001001000110 &
b10000011111000010110001001000110 4
b10000011111000010110001001000110 8
1)
#77000
0)
#77500
b10010001110010000111111001111111 6
b1011001010010101 '
b1011001010010101 3
b10001000010010001110010000111 7
b1100011110101011 $
b1100011110101011 5
b10000000101111110110000111111000 &
b10000000101111110110000111111000 4
b10000000101111110110000111111000 8
b1000011 -
b1000011 1
b1000011 ,
1)
#78000
0)
#78500
b1101101010010000 $
b1101101010010000 5
b11110110011100010110011010100000 7
b100000101011010 '
b100000101011010 3
b10001000001110011110010100011111 6
b1000100 ,
b1000100 1
b1000100 -
b10010001110010000111111001111111 &
b10010001110010000111111001111111 4
b10010001110010000111111001111111 8
1)
#79000
0)
#79500
b10100010111010010001001010011010 6
b110100000001101 '
b110100000001101 3
b11010101011110010110101111011 7
b100000110100111 $
b100000110100111 5
b10001000001110011110010100011111 &
b10001000001110011110010100011111 4
b10001000001110011110010100011111 8
b1000101 -
b1000101 1
b1000101 ,
1)
#80000
0)
#80500
b1000100111111110 $
b1000100111111110 5
b1110100010100101000100010110 7
b1110000001110101 '
b1110000001110101 3
b10110001011100110110001110110000 6
b1000110 ,
b1000110 1
b1000110 -
b10100010111010010001001010011010 &
b10100010111010010001001010011010 4
b10100010111010010001001010011010 8
1)
#81000
0)
#81500
b10110001111110010001011101100100 6
b110100010101100 '
b110100010101100 3
b100001011011001110110100 7
b101000111 $
b101000111 5
b10110001011100110110001110110000 &
b10110001011100110110001110110000 4
b10110001011100110110001110110000 8
b1000111 -
b1000111 1
b1000111 ,
1)
#82000
0)
#82500
b101111111001100 $
b101111111001100 5
b11011111100000010000001110101100 7
b1010100100101001 '
b1010100100101001 3
b10010001011110100001101100010000 6
b1001000 ,
b1001000 1
b1001000 -
b10110001111110010001011101100100 &
b10110001111110010001011101100100 4
b10110001111110010001011101100100 8
1)
#83000
0)
